<?xml version="1.0" encoding="UTF-8"?>
<participations>
    <participation>
        <contest>
            <id>
                1
            </id>
        </contest>
        <user>
            <id>
                5
            </id>
        </user>
    </participation>
    <participation>
        <contest>
            <id>
                1
            </id>
        </contest>
        <user>
            <id>
                7
            </id>
        </user>
    </participation>
    <participation>
        <contest>
            <id>
                2
            </id>
        </contest>
        <user>
            <id>
                5
            </id>
        </user>
    </participation>
    <participation>
        <contest>
            <id>
                1
            </id>
        </contest>
        <user>
            <id>
                3
            </id>
        </user>
    </participation>
    <participation>
        <contest>
            <id>
                1
            </id>
        </contest>
        <user>
            <id>
                7
            </id>
        </user>
    </participation>
    <participation>
        <contest>
            <id>
                2
            </id>
        </contest>
        <user>
            <id>
                7
            </id>
        </user>
    </participation>
    <participation>
        <contest>
            <id>
                2
            </id>
        </contest>
        <user>
            <id>
                3
            </id>
        </user>
    </participation>
</participations>